fave_recode/__init__.py
fave_recode/fave_recode.py
fave_recode/labelset_parser.py
fave_recode/relations.py
fave_recode/resources/cmu2labov.yml
fave_recode/resources/cmu2phila.yml
fave_recode/resources/cmu_parser.yml
fave_recode/rule_classes.py
fave_recode/ruleschema.py
fave_recode/schemes.py
fave_recode-0.3.3.dist-info/LICENSE.md
fave_recode-0.3.3.dist-info/METADATA
fave_recode-0.3.3.dist-info/WHEEL
fave_recode-0.3.3.dist-info/entry_points.txt
fave_recode-0.3.3.dist-info/RECORD
