Metadata-Version: 2.3
Name: fave-recode
Version: 0.3.3
Summary: A package for recoding Praat TextGrids
License: GPLv3
Author: JoFrhwld
Author-email: JoFrhwld@gmail.com
Requires-Python: >=3.10,<4.0
Classifier: License :: Other/Proprietary License
Classifier: Programming Language :: Python :: 3
Classifier: Programming Language :: Python :: 3.10
Classifier: Programming Language :: Python :: 3.11
Classifier: Programming Language :: Python :: 3.12
Classifier: Programming Language :: Python :: 3.13
Requires-Dist: aligned-textgrid (>=0.8,<0.9)
Requires-Dist: cerberus (>=1.3.5,<2.0.0)
Requires-Dist: click (>=8.1.7,<9.0.0)
Requires-Dist: cloup (>=3.0.2,<4.0.0)
Requires-Dist: pyyaml (>=6.0,<7.0)
Project-URL: Homepage, https://forced-alignment-and-vowel-extraction.github.io/fave-recode
Project-URL: Repository, https://github.com/Forced-Alignment-and-Vowel-Extraction/fave-recode
